HBV_Lab/HBV_model.py
HBV_Lab/__init__.py
HBV_Lab/calibration.py
HBV_Lab/hbv_step.py
HBV_Lab/response.py
HBV_Lab/routing.py
HBV_Lab/snow.py
HBV_Lab/soil.py
HBV_Lab/uncertainty.py
hbv_lab-1.0.0.dist-info/licenses/LICENSE
hbv_lab-1.0.0.dist-info/METADATA
hbv_lab-1.0.0.dist-info/WHEEL
hbv_lab-1.0.0.dist-info/top_level.txt
hbv_lab-1.0.0.dist-info/RECORD
