Metadata-Version: 2.4
Name: HBV_Lab
Version: 1.0.0
Summary: An intuitive, object-oriented and user-friendly Python implementation of a lumped conceptual HBV hydrological model for educational and research purposes.
Home-page: https://github.com/abdallaox/HBV_python_implementation
Author: Abdalla Mohammed
Author-email: abdalla.mohammed.ox@gmail.com
License: MIT
Keywords: hydrology HBV-model rainfall-runoff hydrological-modelling
Classifier: Programming Language :: Python :: 3
Classifier: License :: OSI Approved :: MIT License
Classifier: Operating System :: OS Independent
Classifier: Intended Audience :: Science/Research
Classifier: Topic :: Scientific/Engineering :: Hydrology
Requires-Python: >=3.7
License-File: LICENSE
Requires-Dist: numpy
Requires-Dist: pandas
Requires-Dist: matplotlib
Requires-Dist: scipy
Requires-Dist: tqdm
Dynamic: author
Dynamic: author-email
Dynamic: classifier
Dynamic: description
Dynamic: description-content-type
Dynamic: home-page
Dynamic: keywords
Dynamic: license
Dynamic: license-file
Dynamic: requires-dist
Dynamic: requires-python
Dynamic: summary
